os1/__init__.py
os1/__main__.py
os1/core.py
os1/gui.py
os1/packet.py
os1/server.py
os1/utils.py
ouster_os1-1.1.1.dist-info/LICENSE
ouster_os1-1.1.1.dist-info/METADATA
ouster_os1-1.1.1.dist-info/WHEEL
ouster_os1-1.1.1.dist-info/top_level.txt
ouster_os1-1.1.1.dist-info/RECORD
