Metadata-Version: 2.1
Name: ouster-os1
Version: 1.1.1
Summary: Python client for the Ouster Lidar OS-1
Home-page: https://github.com/rsiemens/ouster-python/
Author: Ryan Siemens
Author-email: ryanjsiemens@gmail.com
License: UNKNOWN
Platform: UNKNOWN
Classifier: Programming Language :: Python :: 3
Classifier: License :: OSI Approved :: MIT License
Classifier: Operating System :: OS Independent
